{
    "countries": [
      {
        "id": 1,
        "name": "Australia",
        "cities": [
          {
            "name": "Sydney, Australia",
            "imageUrl": "https://a.travel-assets.com/findyours-php/viewfinder/images/res70/474000/474916-Sydney-Opera-House.jpg",
            "description": "A vibrant city known for its iconic landmarks like the Sydney Opera House and Sydney Harbour Bridge."
          },
          {
            "name": "Melbourne, Australia",
            "imageUrl": "https://encrypted-tbn0.gstatic.com/images?q=tbn:ANd9GcTYpT7yUdg9ShakjXOro4SrJ9IuNSIatqrdIg&s",
            "description": "A cultural hub famous for its art, food, and diverse neighborhoods."
          }
        ]
      },
      {
        "id": 2,
        "name": "Japan",
        "cities": [
          {
            "name": "Tokyo, Japan",
            "imageUrl": "https://encrypted-tbn0.gstatic.com/images?q=tbn:ANd9GcSMd55dBWeP2xZNfVzGYUjEHYyGIJMkFhBOwg&s",
            "description": "A bustling metropolis blending tradition and modernity, famous for its cherry blossoms and rich culture."
          },
          {
            "name": "Kyoto, Japan",
            "imageUrl": "https://encrypted-tbn0.gstatic.com/images?q=tbn:ANd9GcS5qejMvY0qxWQ6AqLrGqC2XXExlK3SC_9JVw&s",
            "description": "Known for its historic temples, gardens, and traditional tea houses."
          }
        ]
      },
      {
        "id": 3,
        "name": "Brazil",
        "cities": [
          {
            "name": "Rio de Janeiro, Brazil",
            "imageUrl": "https://encrypted-tbn0.gstatic.com/images?q=tbn:ANd9GcQmyWU7INczchcLkind70ZA0xaNhxI4NsRt3g&s",
            "description": "A lively city known for its stunning beaches, vibrant carnival celebrations, and iconic landmarks."
          },
          {
            "name": "São Paulo, Brazil",
            "imageUrl": "https://lp-cms-production.imgix.net/2025-09/shutterstock2492777801.jpg?auto=compress&format=auto&fit=crop&q=50&w=1200&h=800",
            "description": "The financial hub with diverse culture, arts, and a vibrant nightlife."
          }
        ]
      }
    ],
    "temples": [
      {
        "id": 1,
        "name": "Angkor Wat, Cambodia",
        "imageUrl": "https://cdn.britannica.com/35/171035-050-8423095A/Angkor-Wat-Siemreab-Cambodia.jpg",
        "description": "A UNESCO World Heritage site and the largest religious monument in the world."
      },
      {
        "id": 2,
        "name": "Taj Mahal, India",
        "imageUrl": "https://encrypted-tbn0.gstatic.com/images?q=tbn:ANd9GcRIMq0Utl9O-TUtLMs4xn6n1q0jyqAYN0YB3w&s",
        "description": "An iconic symbol of love and a masterpiece of Mughal architecture."
      }
    ],
    "beaches": [
      {
        "id": 1,
        "name": "Bora Bora, French Polynesia",
        "imageUrl": "https://www.tahititourisme.fr/app/uploads/2023/06/bora-bora-la-perle-du-pacifique-a-stephane-mailion-photography.webp",
        "description": "An island known for its stunning turquoise waters and luxurious overwater bungalows."
      },
      {
        "id": 2,
        "name": "Copacabana Beach, Brazil",
        "imageUrl": "https://encrypted-tbn0.gstatic.com/images?q=tbn:ANd9GcT2sK_pBn87mZAPsvGMEf8fjvaLGylyT7ZvZQ&s",
        "description": "A famous beach in Rio de Janeiro, Brazil, with a vibrant atmosphere and scenic views."
      }
    ]
  }
